CorrectCvss/__init__.py
CorrectCvss/correct_cvss.py
CorrectCvss-1.1.dist-info/METADATA
CorrectCvss-1.1.dist-info/WHEEL
CorrectCvss-1.1.dist-info/top_level.txt
CorrectCvss-1.1.dist-info/RECORD
