Metadata-Version: 2.1
Name: CorrectCvss
Version: 1.1
Summary: Verify the CVSS vector specification and receive JSON data to generate a CVSS vector.
Home-page: https://github.com/bobolehe/CorrectCvss
Author: bole
Author-email: bobolehe@gmail.com
Classifier: Programming Language :: Python :: 3
Classifier: License :: OSI Approved :: MIT License
Classifier: Operating System :: OS Independent
Requires-Python: >=3.10
Requires-Dist: cvss (==3.1)
